{
  "Starter": [
    {
      "nbt": "{\"akashictome:is_morphing\":1b,\"akashictome:data\":{guideapi:{id:\"guideapi:woot-guide\",Count:1b,tag:{\"akashictome:definedMod\":\"guideapi\"},Damage:0s},extrautils2:{id:\"extrautils2:book\",Count:1b,tag:{\"akashictome:definedMod\":\"extrautils2\"},Damage:0s},thermalfoundation:{id:\"thermalfoundation:tome_lexicon\",Count:1b,tag:{\"akashictome:definedMod\":\"thermalfoundation\"},Damage:0s},actuallyadditions:{id:\"actuallyadditions:item_booklet\",Count:1b,tag:{\"akashictome:definedMod\":\"actuallyadditions\"},Damage:0s},questbook:{id:\"questbook:itemquestbook\",Count:1b,tag:{\"akashictome:definedMod\":\"questbook\"},Damage:0s},techreborn:{id:\"techreborn:techmanuel\",Count:1b,tag:{\"akashictome:definedMod\":\"techreborn\"},Damage:0s},rftools:{id:\"rftools:rftools_manual\",Count:1b,tag:{\"akashictome:definedMod\":\"rftools\"},Damage:0s},modcurrency:{id:\"modcurrency:guidebook\",Count:1b,tag:{\"akashictome:definedMod\":\"modcurrency\"},Damage:0s},cookingforblockheads:{id:\"cookingforblockheads:recipe_book\",Count:1b,tag:{\"akashictome:definedMod\":\"cookingforblockheads\"},Damage:1s},forestry:{id:\"forestry:book_forester\",Count:1b,tag:{\"akashictome:definedMod\":\"forestry\"},Damage:0s},rftools1:{id:\"rftools:rftools_shape_manual\",Count:1b,tag:{\"akashictome:definedMod\":\"rftools1\"},Damage:0s}}}",
      "item": "akashictome:tome",
      "type": "minecraft:item_nbt"
    },
    {
      "item": "minecraft:apple",
      "count": 16
    },
    {
      "nbt": "{inventory:{Size:36,Items:[{Slot:18,id:\"modcurrency:banknote\",Count:1b,Damage:3s}]},full:3}",
      "item": "modcurrency:wallet",
      "data": 3,
      "type": "minecraft:item_nbt"
    }
  ]
}